jsontosqlalchemy/__init__.py
jsontosqlalchemy/extraction.py
jsontosqlalchemy/inserction.py
jsontosqlalchemy-1.0.dist-info/LICENSE
jsontosqlalchemy-1.0.dist-info/METADATA
jsontosqlalchemy-1.0.dist-info/WHEEL
jsontosqlalchemy-1.0.dist-info/top_level.txt
jsontosqlalchemy-1.0.dist-info/RECORD
