Metadata-Version: 2.1
Name: jsontosqlalchemy
Version: 1.0
Summary: Extract any Json to models sqlalchemy
Home-page: https://github.com/CarlosRCDev/jsontosqlalchemy
Author: Carlos Rodriguez
Author-email: diablocharly@hotmail.com
License: UNKNOWN
Download-URL: https://github.com/CarlosRCDev/jsontosqlalchemy/archive/1.0.tar.gz
Platform: UNKNOWN
Classifier: Programming Language :: Python :: 3
Classifier: License :: OSI Approved :: MIT License
Classifier: Operating System :: OS Independent
Requires-Dist: numpy
Requires-Dist: sqlalchemy
